cozify/Error.py
cozify/__init__.py
cozify/cloud.py
cozify/cloud_api.py
cozify/config.py
cozify/hub.py
cozify/hub_api.py
cozify/multisensor.py
cozify/test/.gitignore
cozify/test/__init__.py
cozify/test/debug.py
cozify/test/fixtures.py
cozify/test/fixtures_devices.py
cozify/test/test_cloud.py
cozify/test/test_cloud_api.py
cozify/test/test_config.py
cozify/test/test_hub.py
cozify/test/test_hub_api.py
cozify/test/test_hub_device_capabilities.py
cozify/test/test_hub_devices.py
cozify/test/test_hub_scenes.py
cozify-0.2.36.dist-info/LICENSE
cozify-0.2.36.dist-info/METADATA
cozify-0.2.36.dist-info/WHEEL
cozify-0.2.36.dist-info/RECORD
