Metadata-Version: 2.1
Name: cozify
Version: 0.2.36
Summary: Unofficial Python3 API bindings for the (unpublished) Cozify API.
Home-page: https://github.com/Artanicus/python-cozify
License: MIT
Author: Artanicus
Author-email: artanicus@nocturnal.fi
Requires-Python: >=3.8.1,<4.0.0
Classifier: License :: OSI Approved :: MIT License
Classifier: Programming Language :: Python :: 3
Classifier: Programming Language :: Python :: 3.9
Classifier: Programming Language :: Python :: 3.10
Classifier: Programming Language :: Python :: 3.11
Requires-Dist: absl-py (>=1.0.0,<2.0.0)
Requires-Dist: requests (>=2.27.1,<3.0.0)
Project-URL: Repository, https://github.com/Artanicus/python-cozify
